tkinter_manager/__init__.py
tkinter_manager/bindings.py
tkinter_manager/button_manager.py
tkinter_manager/checkbox_manager.py
tkinter_manager/container_manager.py
tkinter_manager/dropdown_manager.py
tkinter_manager/label_manager.py
tkinter_manager/layout_manager.py
tkinter_manager/progress_bar_manager.py
tkinter_manager/radio_button_manager.py
tkinter_manager/text_input_manager.py
tkinter_manager/tkinter_element.py
tkinter_manager/tkinter_manager.py
tkinter_manager/utils.py
tkinter_manager/config/resources.json
tkinter_manager-0.3.1.dist-info/LICENSE
tkinter_manager-0.3.1.dist-info/METADATA
tkinter_manager-0.3.1.dist-info/WHEEL
tkinter_manager-0.3.1.dist-info/top_level.txt
tkinter_manager-0.3.1.dist-info/RECORD
