Metadata-Version: 2.1
Name: tkinter_manager
Version: 0.3.1
Home-page: https://github.com/ScriptedChicken/TKinter-Manager
License-File: LICENSE
Provides-Extra: dev
Requires-Dist: pytest ; extra == 'dev'
Requires-Dist: black ; extra == 'dev'
